airfogsim/agent/__init__.py
airfogsim/agent/delivery_agent.py
airfogsim/agent/delivery_drone.py
airfogsim/agent/delivery_station.py
airfogsim/agent/drone.py
airfogsim/agent/inspection_station.py
airfogsim/agent/sensing_agent.py
airfogsim/agent/terminal.py
airfogsim/cli/__init__.py
airfogsim/cli/main.py
airfogsim/cli/test_cli.py
airfogsim/component/__init__.py
airfogsim/component/charging.py
airfogsim/component/communication.py
airfogsim/component/computation.py
airfogsim/component/em_sensor.py
airfogsim/component/img_sensor.py
airfogsim/component/logistics.py
airfogsim/component/mobility.py
airfogsim/component/object_sensor.py
airfogsim/core/__init__.py
airfogsim/core/agent.py
airfogsim/core/component.py
airfogsim/core/dataprovider.py
airfogsim/core/enums.py
airfogsim/core/environment.py
airfogsim/core/event.py
airfogsim/core/llm_client.py
airfogsim/core/resource.py
airfogsim/core/task.py
airfogsim/core/trigger.py
airfogsim/core/utils.py
airfogsim/core/workflow.py
airfogsim/dataprovider/__init__.py
airfogsim/dataprovider/osm_to_sumo.py
airfogsim/dataprovider/signal.py
airfogsim/dataprovider/signal_integration.py
airfogsim/dataprovider/traffic.py
airfogsim/dataprovider/weather.py
airfogsim/dataprovider/weather_integration.py
airfogsim/dataprovider/api_adapters/__init__.py
airfogsim/dataprovider/api_adapters/openweathermap_adapter.py
airfogsim/event/resource.py
airfogsim/examples/example_benchmark_multi_workflow.py
airfogsim/examples/example_frequency_signal_integration.py
airfogsim/examples/example_object_sensor.py
airfogsim/examples/example_signal_sensing.py
airfogsim/examples/example_simulation_traffic.py
airfogsim/examples/example_task_duplicate_check.py
airfogsim/examples/example_task_priority.py
airfogsim/examples/example_task_queue_sort.py
airfogsim/examples/example_trigger_basic.py
airfogsim/examples/example_weather_at_position.py
airfogsim/examples/example_weather_openweathermap.py
airfogsim/examples/example_weather_provider.py
airfogsim-1.1.1.dist-info/licenses/LICENSE
airfogsim-1.1.1.dist-info/METADATA
airfogsim-1.1.1.dist-info/WHEEL
airfogsim-1.1.1.dist-info/entry_points.txt
airfogsim-1.1.1.dist-info/top_level.txt
airfogsim-1.1.1.dist-info/RECORD
