Metadata-Version: 2.4
Name: airfogsim
Version: 1.1.1
Summary: Low Altitude Space Simulation System
Author-email: Zhiwei Wei <2311769@tongji.edu.cn>
Requires-Python: >=3.8
License-File: LICENSE
Requires-Dist: simpy
Requires-Dist: numpy
Requires-Dist: pint
Requires-Dist: python-dotenv
Requires-Dist: gunicorn
Requires-Dist: requests
Requires-Dist: pandas
Requires-Dist: openai
Requires-Dist: tqdm
Requires-Dist: fastapi
Requires-Dist: tabulate
Requires-Dist: pydantic
Requires-Dist: uvicorn[standard]
Provides-Extra: dev
Requires-Dist: pytest; extra == "dev"
Requires-Dist: pytest-cov; extra == "dev"
Requires-Dist: pytest-asyncio; extra == "dev"
Requires-Dist: black; extra == "dev"
Requires-Dist: flake8; extra == "dev"
Requires-Dist: pip-tools; extra == "dev"
Provides-Extra: docs
Requires-Dist: sphinx>=4.0; extra == "docs"
Requires-Dist: sphinx-rtd-theme; extra == "docs"
Requires-Dist: sphinx-autodoc-typehints; extra == "docs"
Requires-Dist: myst-parser; extra == "docs"
Requires-Dist: sphinx-copybutton; extra == "docs"
Dynamic: license-file
